{
	"backtraceGraph" : 
	{
		"commands" : 
		[
			"_install",
			"install"
		],
		"files" : 
		[
			"/opt/ros/humble/share/ament_cmake_core/cmake/symlink_install/install.cmake",
			"python/pybind11/CMakeLists.txt"
		],
		"nodes" : 
		[
			{
				"file" : 1
			},
			{
				"command" : 1,
				"file" : 1,
				"line" : 317,
				"parent" : 0
			},
			{
				"command" : 0,
				"file" : 0,
				"line" : 43,
				"parent" : 1
			}
		]
	},
	"installers" : 
	[
		{
			"backtrace" : 2,
			"component" : "Unspecified",
			"destination" : "share/moveit_task_constructor_core/cmake",
			"exportName" : "pybind11Targets",
			"exportTargets" : 
			[
				{
					"id" : "pybind11_headers::@c9941ed53ee12615eb55",
					"index" : 0
				}
			],
			"paths" : 
			[
				"python/pybind11/CMakeFiles/Export/share/moveit_task_constructor_core/cmake/pybind11Targets.cmake"
			],
			"type" : "export"
		}
	],
	"paths" : 
	{
		"build" : "python/pybind11",
		"source" : "python/pybind11"
	}
}
